{"sections":{"main":{"type":"main-product","blocks":{"rating_stars_G3iHza":{"type":"rating-stars","name":"t:rating_stars","settings":{"show_on_display":"desktop_and_mobile","product":"","hide_rating_when_no_reviews":true,"rating":4.9,"show_note":true,"show_review_count":false,"review_count":0,"link":"#reviews","margin_top":0,"margin_bottom":0,"additional_class":""},"blocks":{}},"text_zLqMQw":{"type":"text","name":"t:title","settings":{"show_on_display":"desktop_and_mobile","text":"<p>{{ product.title }}<\/p>","text_style":"h3","paragraph_font_size":"normal","font_weight":400,"alignment":"left","alignment_mobile":"left","show_read_more":false,"read_more_length":200,"read_more_text":"Voir plus","read_less_text":"Voir moins","truncate":false,"truncate_length":2,"margin_top":0,"margin_bottom":0,"additional_class":""},"blocks":{}},"badges_YarrNm":{"type":"badges","name":"t:badges","settings":{"show_on_display":"desktop_and_mobile","alignment_desktop":"flex-start","alignment_mobile":"flex-start","additional_class":""},"blocks":{"badge_hNAExC":{"type":"_badge","settings":{"show_on_display":"desktop_and_mobile","text":"Répare les ongles abîmés en portant","badge_style":"secondary","icon":"none","icon_custom":"","icon_position":"end","additional_class":""},"blocks":{}},"badge_Gj7aqa":{"type":"_badge","settings":{"show_on_display":"desktop_and_mobile","text":"Sans UV · Pose en 5 minutes","badge_style":"secondary","icon":"none","icon_custom":"","icon_position":"end","additional_class":""},"blocks":{}},"badge_Nna3Je":{"type":"_badge","settings":{"show_on_display":"desktop_and_mobile","text":"Technologie K-Beauty brevetée 🇰🇷","badge_style":"secondary","icon":"none","icon_custom":"","icon_position":"end","additional_class":""},"blocks":{}}},"block_order":["badge_hNAExC","badge_Gj7aqa","badge_Nna3Je"]},"stories_TChHcD":{"type":"stories","name":"t:stories","settings":{"show_on_display":"desktop_and_mobile","alignment":"flex-start","alignment_mobile":"flex-start","margin_top":10,"margin_bottom":10,"additional_class":""},"blocks":{"story_KRC3dq":{"type":"_story","settings":{"title":"Story","media_type_1":"video","image_duration_1":5,"media_type_2":"video","image_duration_2":5,"media_type_3":"video","image_duration_3":5,"media_type_4":"video","image_duration_4":5,"media_type_5":"video","image_duration_5":5,"media_type_6":"video","image_duration_6":5,"media_type_7":"video","image_duration_7":5,"media_type_8":"video","image_duration_8":5},"blocks":{}},"story_wTrY8A":{"type":"_story","settings":{"title":"Story","media_type_1":"video","image_duration_1":5,"media_type_2":"video","image_duration_2":5,"media_type_3":"video","image_duration_3":5,"media_type_4":"video","image_duration_4":5,"media_type_5":"video","image_duration_5":5,"media_type_6":"video","image_duration_6":5,"media_type_7":"video","image_duration_7":5,"media_type_8":"video","image_duration_8":5},"blocks":{}},"story_yhiH9Q":{"type":"_story","settings":{"title":"Story","media_type_1":"video","image_duration_1":5,"media_type_2":"video","image_duration_2":5,"media_type_3":"video","image_duration_3":5,"media_type_4":"video","image_duration_4":5,"media_type_5":"video","image_duration_5":5,"media_type_6":"video","image_duration_6":5,"media_type_7":"video","image_duration_7":5,"media_type_8":"video","image_duration_8":5},"blocks":{}}},"block_order":["story_KRC3dq","story_wTrY8A","story_yhiH9Q"]},"group_ALWCwg":{"type":"group","name":"t:icons_and_text_inline","settings":{"show_on_display":"desktop_and_mobile","wrap_in_card":false,"color_scheme":"","show_card_border":false,"layout_type":"flex","width_desktop":100,"layout_direction_desktop":"column","layout_grid_columns_desktop":3,"layout_gap_desktop":10,"layout_wrap_desktop":"nowrap","layout_justify_desktop":"flex-start","layout_align_items_desktop":"flex-start","same_as_desktop":true,"width_mobile":100,"layout_direction_mobile":"column","layout_grid_columns_mobile":1,"layout_gap_mobile":10,"layout_wrap_mobile":"nowrap","layout_justify_mobile":"flex-start","layout_align_items_mobile":"flex-start","use_global_container_padding":true,"padding_horizontal":30,"padding_vertical":30,"margin_top":5,"margin_bottom":5,"additional_class":""},"blocks":{"icon_with_text_RUhfrk":{"type":"icon-with-text","name":"t:icon_with_text","settings":{"show_on_display":"desktop_and_mobile","layout_direction_desktop":"row","layout_gap_desktop":5,"same_as_desktop":true,"layout_direction_mobile":"column","layout_gap_mobile":10,"icon_type":"icon","icon":"none","icon_custom":"","icon_size":22,"icon_position":"start","text":"<p>🌿 <strong>Ongles réparés, pas juste couverts<\/strong> — Le soin actif pénètre l'ongle pendant toute la durée du port<\/p>","text_style":"paragraph","font_weight":400,"margin_top":0,"margin_bottom":0,"additional_class":""},"blocks":{}},"icon_with_text_dXzFdQ":{"type":"icon-with-text","name":"t:icon_with_text","settings":{"show_on_display":"desktop_and_mobile","layout_direction_desktop":"row","layout_gap_desktop":5,"same_as_desktop":true,"layout_direction_mobile":"column","layout_gap_mobile":10,"icon_type":"icon","icon":"none","icon_custom":"","icon_size":22,"icon_position":"start","text":"<p>✨ <strong>Brillance professionnelle à la maison<\/strong> — Rendu gel sans salon, sans UV, sans matériel<\/p>","text_style":"paragraph","font_weight":400,"margin_top":0,"margin_bottom":0,"additional_class":""},"blocks":{}},"icon_with_text_gU9EEn":{"type":"icon-with-text","name":"t:icon_with_text","settings":{"show_on_display":"desktop_and_mobile","layout_direction_desktop":"row","layout_gap_desktop":5,"same_as_desktop":true,"layout_direction_mobile":"column","layout_gap_mobile":10,"icon_type":"icon","icon":"none","icon_custom":"","icon_size":22,"icon_position":"start","text":"<p>⏱️ <strong>5 minutes chrono<\/strong> — Pour toutes celles qui n'ont pas le temps, mais qui refusent de sacrifier le style<\/p>","text_style":"paragraph","font_weight":400,"margin_top":0,"margin_bottom":0,"additional_class":""},"blocks":{}}},"block_order":["icon_with_text_RUhfrk","icon_with_text_dXzFdQ","icon_with_text_gU9EEn"]},"product_form_grYQk6":{"type":"_product-form","name":"t:product_form","settings":{},"blocks":{"product_variant_picker_xWC3wF":{"type":"_product-variant-picker","name":"t:product_variant_picker","settings":{"show_option_name":true,"variant_picker_type":"selects","show_swatches":true,"swatches_size":"normal","swatches_rounded":true,"margin_top":0,"margin_bottom":15,"additional_class":""},"blocks":{"product-variant-popup":{"type":"_product-variant-popup","disabled":true,"static":true,"settings":{"show_on_display":"desktop_and_mobile","show_on_option_name":"Taille","color_scheme":"scheme-1","button_style":"button","button_label":"Guide des tailles","icon":"straighten","icon_custom":"","icon_position":"end","additional_class":""},"blocks":{"text_LfyX9A":{"type":"text","name":"t:title","settings":{"show_on_display":"desktop_and_mobile","text":"<h1>Guide des tailles<\/h1>","text_style":"h3","paragraph_font_size":"normal","font_weight":400,"alignment":"left","alignment_mobile":"left","show_read_more":false,"read_more_length":200,"read_more_text":"Voir plus","read_less_text":"Voir moins","truncate":false,"truncate_length":2,"margin_top":0,"margin_bottom":10,"additional_class":""},"blocks":{}},"text_99rHbT":{"type":"text","name":"t:text","settings":{"show_on_display":"desktop_and_mobile","text":"<p>Lorem ipsum dolor sit amet, consectetur adipiscing elit, sed do eiusmod tempor incididunt ut labore et dolore magna aliqua. Ut enim ad minim veniam, quis nostrud exercitation ullamco laboris nisi ut aliquip ex ea commodo consequat.<\/p>","text_style":"paragraph","paragraph_font_size":"normal","font_weight":400,"alignment":"left","alignment_mobile":"left","show_read_more":false,"read_more_length":200,"read_more_text":"Voir plus","read_less_text":"Voir moins","truncate":false,"truncate_length":2,"margin_top":0,"margin_bottom":0,"additional_class":""},"blocks":{}}},"block_order":["text_LfyX9A","text_99rHbT"]}},"block_order":[]},"quantity_breaks_jJweMy":{"type":"_quantity-breaks","name":"t:quantity_breaks_columns","disabled":true,"settings":{"show_on_display":"desktop_and_mobile","label":"Quantité:","show_variant_picker":false,"show_variant_thumbnail":true,"display_mode":"column","quantity_selected_by_default":1,"margin_top":0,"margin_bottom":10,"additional_class":""},"blocks":{"quantity_breaks_item_bUjWdt":{"type":"_quantity-breaks-item","name":"t:quantity_breaks_item","settings":{"quantity":1,"discount_type":"none","discount_value":"","discount_percentage":20,"cross_sell_products":[],"badge":"","badge_position":"top","badge_display":"normal","product_small_title":"article","product_small_title_plural":"articles","badge_next_to_title":"","show_unit_price":false,"unit_price_text":"par article","description":"","description_position":"below_price","show_image":true,"image_width":70,"show_image_badge":true,"image_badge_position":"bottomright"},"blocks":{}},"quantity_breaks_item_HwDpxw":{"type":"_quantity-breaks-item","name":"t:quantity_breaks_item","settings":{"quantity":2,"discount_type":"percentage","discount_value":"","discount_percentage":5,"cross_sell_products":[],"badge":"-5%","badge_position":"top","badge_display":"overlap","product_small_title":"article","product_small_title_plural":"articles","badge_next_to_title":"","show_unit_price":false,"unit_price_text":"par article","description":"","description_position":"below_price","show_image":true,"image_width":70,"show_image_badge":true,"image_badge_position":"bottomright"},"blocks":{}},"quantity_breaks_item_m3DEcc":{"type":"_quantity-breaks-item","name":"t:quantity_breaks_item","settings":{"quantity":3,"discount_type":"percentage","discount_value":"","discount_percentage":10,"cross_sell_products":[],"badge":"-10%","badge_position":"top","badge_display":"overlap","product_small_title":"article","product_small_title_plural":"articles","badge_next_to_title":"","show_unit_price":false,"unit_price_text":"par article","description":"","description_position":"below_price","show_image":true,"image_width":70,"show_image_badge":true,"image_badge_position":"bottomright"},"blocks":{}}},"block_order":["quantity_breaks_item_bUjWdt","quantity_breaks_item_HwDpxw","quantity_breaks_item_m3DEcc"]},"toggle_cross_sell_VK6w3f":{"type":"_toggle-cross-sell","name":"t:toggle_cross_sell","settings":{"show_on_display":"desktop_and_mobile","title":"Ajouter des options","description":"","product_list":["produit-complementaire-dexemple"],"toggle_mode":"checkbox","show_image":false,"margin_top":0,"margin_bottom":10,"additional_class":""},"blocks":{}},"subscription_pmYpT3":{"type":"_subscription","name":"t:subscription","disabled":true,"settings":{"show_on_display":"desktop_and_mobile","label":"Choisissez votre option :","options_order":"one_time_first","default_selected":"one_time","one_time_label":"Achat unique","one_time_description":"","subscription_label":"S'abonner","frequency_picker_type":"buttons","sales_badge":"percentage","subscription_description":"<ul><li>Pause ou annulation à tout moment<\/li><li>Garantie satisfait ou remboursé sous 30 jours<\/li><\/ul>","margin_top":0,"margin_bottom":10,"additional_class":""},"blocks":{}},"product-add-to-cart-button":{"type":"_product-add-to-cart-button","static":true,"settings":{"enable_sticky_add_to_cart":true,"button_style":"primary","show_price":true,"icon":"none","icon_custom":"","icon_position":"end","additional_class":""},"blocks":{"product-quantity-selector":{"type":"_product-quantity-selector","disabled":true,"static":true,"settings":{"show_on_display":"desktop_and_mobile","additional_class":""},"blocks":{}},"add-to-wishlist-button":{"type":"_add-to-wishlist-button","static":true,"settings":{},"blocks":{}}},"block_order":[]},"accelerated-checkout":{"type":"_accelerated-checkout","disabled":true,"static":true,"settings":{"show_on_display":"desktop_and_mobile","full_width":true,"button_style":"primary","margin_top":0,"margin_bottom":0,"additional_class":""},"blocks":{}}},"block_order":["product_variant_picker_xWC3wF","quantity_breaks_jJweMy","toggle_cross_sell_VK6w3f","subscription_pmYpT3"]},"payment_methods_BdjpFB":{"type":"payment-methods","name":"t:payment_methods","settings":{"show_on_display":"desktop_and_mobile","alignment_desktop":"center","alignment_mobile":"flex-start","icon_size":35,"margin_top":10,"margin_bottom":10,"additional_class":""},"blocks":{}},"accordions_TjeNrK":{"type":"accordions","name":"t:accordions","settings":{"show_on_display":"desktop_and_mobile","icon":"caret","dividers":true,"additional_class":""},"blocks":{"accordion_4DG3Lx":{"type":"_accordion","settings":{"show_on_display":"desktop_and_mobile","heading":"Politique de retour","open_by_default":false,"icon":"none","icon_custom":"","additional_class":""},"blocks":{"text_WbpQrg":{"type":"text","settings":{"show_on_display":"desktop_and_mobile","text":"<p>Notre objectif est que chaque client soit totalement satisfait de son achat. Si ce n'est pas le cas, faites-le nous savoir et nous ferons de notre mieux pour trouver une solution avec vous.<\/p>","text_style":"paragraph","paragraph_font_size":"normal","font_weight":400,"alignment":"left","alignment_mobile":"left","show_read_more":false,"read_more_length":200,"read_more_text":"Voir plus","read_less_text":"Voir moins","truncate":false,"truncate_length":2,"margin_top":0,"margin_bottom":0,"additional_class":""},"blocks":{}}},"block_order":["text_WbpQrg"]},"accordion_mDYcT9":{"type":"_accordion","settings":{"show_on_display":"desktop_and_mobile","heading":"Livraison","open_by_default":false,"icon":"none","icon_custom":"","additional_class":""},"blocks":{"text_6CRgrf":{"type":"text","settings":{"show_on_display":"desktop_and_mobile","text":"<p>Nous travaillons rapidement pour envoyer votre commande dès que possible. Une fois votre commande expédiée, vous recevrez un email avec des informations supplémentaires. Les délais de livraison varient en fonction de votre emplacement.<\/p>","text_style":"paragraph","paragraph_font_size":"normal","font_weight":400,"alignment":"left","alignment_mobile":"left","show_read_more":false,"read_more_length":200,"read_more_text":"Voir plus","read_less_text":"Voir moins","truncate":false,"truncate_length":2,"margin_top":0,"margin_bottom":0,"additional_class":""},"blocks":{}}},"block_order":["text_6CRgrf"]},"accordion_ypRgbb":{"type":"_accordion","settings":{"show_on_display":"desktop_and_mobile","heading":"Composition","open_by_default":false,"icon":"none","icon_custom":"","additional_class":""},"blocks":{"text_ixTU8G":{"type":"text","settings":{"show_on_display":"desktop_and_mobile","text":"<p>Couche 1 : Gel haute brillance (finition volume)<br\/><br\/>Couche 2 : Support PU (flexible et respirant)<br\/><br\/>Couche 3 : Hydrocolloid médical enrichi en Kératine (soin actif au contact de l'ongle)<\/p>","text_style":"paragraph","paragraph_font_size":"normal","font_weight":400,"alignment":"left","alignment_mobile":"left","show_read_more":false,"read_more_length":200,"read_more_text":"Voir plus","read_less_text":"Voir moins","truncate":false,"truncate_length":2,"margin_top":0,"margin_bottom":0,"additional_class":""},"blocks":{}}},"block_order":["text_ixTU8G"]}},"block_order":["accordion_4DG3Lx","accordion_mDYcT9","accordion_ypRgbb"]},"group_EWd3W6":{"type":"group","name":"t:group","settings":{"show_on_display":"desktop_and_mobile","wrap_in_card":true,"color_scheme":"scheme-2","show_card_border":true,"layout_type":"flex","width_desktop":100,"layout_direction_desktop":"column","layout_grid_columns_desktop":3,"layout_gap_desktop":10,"layout_wrap_desktop":"nowrap","layout_justify_desktop":"flex-start","layout_align_items_desktop":"flex-start","same_as_desktop":true,"width_mobile":100,"layout_direction_mobile":"column","layout_grid_columns_mobile":1,"layout_gap_mobile":10,"layout_wrap_mobile":"nowrap","layout_justify_mobile":"flex-start","layout_align_items_mobile":"flex-start","use_global_container_padding":true,"padding_horizontal":30,"padding_vertical":30,"margin_top":0,"margin_bottom":0,"additional_class":""},"blocks":{"text_XKiT7p":{"type":"text","name":"t:title","disabled":true,"settings":{"show_on_display":"desktop_and_mobile","text":"<h1>Disponible en routine<\/h1>","text_style":"h6","paragraph_font_size":"normal","font_weight":400,"alignment":"left","alignment_mobile":"left","show_read_more":false,"read_more_length":100,"read_more_text":"Voir plus","read_less_text":"Voir moins","truncate":false,"truncate_length":2,"margin_top":0,"margin_bottom":0,"additional_class":""},"blocks":{}},"cross_sell_GfyGgj":{"type":"cross-sell","name":"t:up_sell","settings":{"show_on_display":"desktop_and_mobile","display_mode":"row","color_scheme":"","products":[],"title":"Bundle","description":"<p>Bundle de produits<\/p>","show_image":true,"image_width":75,"show_options_label":false,"margin_top":0,"margin_bottom":0,"additional_class":""},"blocks":{}}},"block_order":["text_XKiT7p","cross_sell_GfyGgj"]},"judge_me_reviews_preview_badge_KBDHzY":{"type":"shopify:\/\/apps\/judge-me-reviews\/blocks\/preview_badge\/61ccd3b1-a9f2-4160-9fe9-4fec8413e5d8","disabled":true,"settings":{}},"product_media_gallery":{"type":"_product-media-gallery","static":true,"settings":{"hide_variants":false,"media_display":"carrousel","media_ratio":"1 \/ 1","media_rounded":true,"grid_columns":"2","grid_gap":10,"main_image_full_width":true,"show_arrows":false,"show_pagination":false,"show_thumbnails":true,"show_thumbnails_on_display":"desktop_and_mobile","thumbnails_show_arrows":false,"video_loop":true,"enable_video_controls":false,"show_badges":false,"additional_class":""},"blocks":{}}},"block_order":["rating_stars_G3iHza","text_zLqMQw","badges_YarrNm","stories_TChHcD","group_ALWCwg","product_form_grYQk6","payment_methods_BdjpFB","accordions_TjeNrK","group_EWd3W6","judge_me_reviews_preview_badge_KBDHzY"],"settings":{"color_scheme":"scheme-1","show_product_info_card":false,"color_scheme_product_info":"","image_position":"row","product_info_width":50,"gap":60,"carrousel_sticky":false,"product_info_sticky":false,"carrousel_full_width":true,"padding_top":30,"padding_bottom":50,"margin_top":0,"margin_bottom":0}},"custom_section_xUHnaD":{"type":"custom-section","blocks":{"text_Hp3DLY":{"type":"text","name":"t:title","settings":{"show_on_display":"desktop_and_mobile","text":"<h2>Application<\/h2>","text_style":"h3","paragraph_font_size":"normal","font_weight":400,"alignment":"left","alignment_mobile":"left","show_read_more":false,"read_more_length":50,"read_more_text":"Voir plus","read_less_text":"Voir moins","truncate":false,"truncate_length":2,"margin_top":0,"margin_bottom":0,"additional_class":""},"blocks":{}},"group_X9cazY":{"type":"group","name":"t:custom_section_columns_name_default","settings":{"show_on_display":"desktop_and_mobile","wrap_in_card":false,"color_scheme":"","show_card_border":false,"layout_type":"flex","width_desktop":100,"layout_direction_desktop":"row","layout_grid_columns_desktop":3,"layout_gap_desktop":10,"layout_wrap_desktop":"nowrap","layout_justify_desktop":"flex-start","layout_align_items_desktop":"flex-start","same_as_desktop":false,"width_mobile":100,"layout_direction_mobile":"column","layout_grid_columns_mobile":1,"layout_gap_mobile":10,"layout_wrap_mobile":"nowrap","layout_justify_mobile":"flex-start","layout_align_items_mobile":"flex-start","use_global_container_padding":true,"padding_horizontal":30,"padding_vertical":30,"margin_top":10,"margin_bottom":10,"additional_class":""},"blocks":{"group_WfmczU":{"type":"group","name":"t:custom_section_column_name_default","settings":{"show_on_display":"desktop_and_mobile","wrap_in_card":true,"color_scheme":"scheme-2","show_card_border":false,"layout_type":"flex","width_desktop":100,"layout_direction_desktop":"column","layout_grid_columns_desktop":3,"layout_gap_desktop":10,"layout_wrap_desktop":"nowrap","layout_justify_desktop":"flex-start","layout_align_items_desktop":"flex-start","same_as_desktop":true,"width_mobile":100,"layout_direction_mobile":"column","layout_grid_columns_mobile":1,"layout_gap_mobile":10,"layout_wrap_mobile":"nowrap","layout_justify_mobile":"flex-start","layout_align_items_mobile":"flex-start","use_global_container_padding":true,"padding_horizontal":30,"padding_vertical":30,"margin_top":10,"margin_bottom":10,"additional_class":""},"blocks":{"image_mK6Dxr":{"type":"image","name":"t:image","settings":{"show_on_display":"desktop_and_mobile","image":"shopify:\/\/shop_images\/Manucure_sans_bavure_16.png","show_placeholder":true,"link":"","image_ratio":"adapt","image_width_desktop":100,"image_width_mobile":100,"additional_class":""},"blocks":{}},"text_rPU8tX":{"type":"text","name":"t:title","settings":{"show_on_display":"desktop_and_mobile","text":"<h1>1. Préparer<\/h1>","text_style":"h5","paragraph_font_size":"normal","font_weight":400,"alignment":"left","alignment_mobile":"left","show_read_more":false,"read_more_length":50,"read_more_text":"Voir plus","read_less_text":"Voir moins","truncate":false,"truncate_length":2,"margin_top":0,"margin_bottom":0,"additional_class":""},"blocks":{}},"text_Xgrp8C":{"type":"text","name":"t:text","settings":{"show_on_display":"desktop_and_mobile","text":"<p>Utilisez la lingette pour enlever toute trace d’huile, saleté ou humidité afin d’assurer une application optimale.<\/p>","text_style":"paragraph","paragraph_font_size":"normal","font_weight":400,"alignment":"left","alignment_mobile":"left","show_read_more":false,"read_more_length":50,"read_more_text":"Voir plus","read_less_text":"Voir moins","truncate":false,"truncate_length":2,"margin_top":0,"margin_bottom":0,"additional_class":""},"blocks":{}}},"block_order":["image_mK6Dxr","text_rPU8tX","text_Xgrp8C"]},"group_RqzRgB":{"type":"group","name":"t:custom_section_column_name_default","settings":{"show_on_display":"desktop_and_mobile","wrap_in_card":true,"color_scheme":"scheme-2","show_card_border":false,"layout_type":"flex","width_desktop":100,"layout_direction_desktop":"column","layout_grid_columns_desktop":3,"layout_gap_desktop":10,"layout_wrap_desktop":"nowrap","layout_justify_desktop":"flex-start","layout_align_items_desktop":"flex-start","same_as_desktop":true,"width_mobile":100,"layout_direction_mobile":"column","layout_grid_columns_mobile":1,"layout_gap_mobile":10,"layout_wrap_mobile":"nowrap","layout_justify_mobile":"flex-start","layout_align_items_mobile":"flex-start","use_global_container_padding":true,"padding_horizontal":30,"padding_vertical":30,"margin_top":10,"margin_bottom":10,"additional_class":""},"blocks":{"image_qkXFBn":{"type":"image","name":"t:image","settings":{"show_on_display":"desktop_and_mobile","image":"shopify:\/\/shop_images\/Manucure_sans_bavure_17.png","show_placeholder":true,"link":"","image_ratio":"adapt","image_width_desktop":100,"image_width_mobile":100,"additional_class":""},"blocks":{}},"text_cC9Wnp":{"type":"text","name":"t:title","settings":{"show_on_display":"desktop_and_mobile","text":"<h1>2. Appliquer<\/h1>","text_style":"h5","paragraph_font_size":"normal","font_weight":400,"alignment":"left","alignment_mobile":"left","show_read_more":false,"read_more_length":50,"read_more_text":"Voir plus","read_less_text":"Voir moins","truncate":false,"truncate_length":2,"margin_top":0,"margin_bottom":0,"additional_class":""},"blocks":{}},"text_jJMm9f":{"type":"text","name":"t:text","settings":{"show_on_display":"desktop_and_mobile","text":"<p>Placez le nail strip sur votre ongle et appuyez fermement le long de la cuticule pour une tenue parfaite.<\/p>","text_style":"paragraph","paragraph_font_size":"normal","font_weight":400,"alignment":"left","alignment_mobile":"left","show_read_more":false,"read_more_length":50,"read_more_text":"Voir plus","read_less_text":"Voir moins","truncate":false,"truncate_length":2,"margin_top":0,"margin_bottom":0,"additional_class":""},"blocks":{}}},"block_order":["image_qkXFBn","text_cC9Wnp","text_jJMm9f"]},"group_nVTqAg":{"type":"group","name":"t:custom_section_column_name_default","settings":{"show_on_display":"desktop_and_mobile","wrap_in_card":true,"color_scheme":"scheme-2","show_card_border":false,"layout_type":"flex","width_desktop":100,"layout_direction_desktop":"column","layout_grid_columns_desktop":3,"layout_gap_desktop":10,"layout_wrap_desktop":"nowrap","layout_justify_desktop":"flex-start","layout_align_items_desktop":"flex-start","same_as_desktop":true,"width_mobile":100,"layout_direction_mobile":"column","layout_grid_columns_mobile":1,"layout_gap_mobile":10,"layout_wrap_mobile":"nowrap","layout_justify_mobile":"flex-start","layout_align_items_mobile":"flex-start","use_global_container_padding":true,"padding_horizontal":30,"padding_vertical":30,"margin_top":10,"margin_bottom":10,"additional_class":""},"blocks":{"image_3h4nRR":{"type":"image","name":"t:image","settings":{"show_on_display":"desktop_and_mobile","image":"shopify:\/\/shop_images\/Manucure_sans_bavure_18.png","show_placeholder":true,"link":"","image_ratio":"adapt","image_width_desktop":100,"image_width_mobile":100,"additional_class":""},"blocks":{}},"text_7di94K":{"type":"text","name":"t:title","settings":{"show_on_display":"desktop_and_mobile","text":"<h1>3. Limer<\/h1>","text_style":"h5","paragraph_font_size":"normal","font_weight":400,"alignment":"left","alignment_mobile":"left","show_read_more":false,"read_more_length":50,"read_more_text":"Voir plus","read_less_text":"Voir moins","truncate":false,"truncate_length":2,"margin_top":0,"margin_bottom":0,"additional_class":""},"blocks":{}},"text_BUnedT":{"type":"text","name":"t:text","settings":{"show_on_display":"desktop_and_mobile","text":"<p>Limez délicatement dans un seul sens pour un résultat net et uniforme.<\/p>","text_style":"paragraph","paragraph_font_size":"normal","font_weight":400,"alignment":"left","alignment_mobile":"left","show_read_more":false,"read_more_length":50,"read_more_text":"Voir plus","read_less_text":"Voir moins","truncate":false,"truncate_length":2,"margin_top":0,"margin_bottom":0,"additional_class":""},"blocks":{}}},"block_order":["image_3h4nRR","text_7di94K","text_BUnedT"]}},"block_order":["group_WfmczU","group_RqzRgB","group_nVTqAg"]}},"block_order":["text_Hp3DLY","group_X9cazY"],"name":"t:multicolumns","settings":{"show_on_display":"desktop_and_mobile","section_width":"normal","color_scheme":"scheme-0960bf69-3705-4c8e-ad7b-cb8e0de43a96","wrap_in_card":false,"color_scheme_card":"","layout_type":"flex","layout_flex_direction_desktop":"column","layout_grid_columns_desktop":3,"layout_gap_desktop":10,"layout_flex_wrap_desktop":"nowrap","layout_flex_justify_desktop":"flex-start","layout_flex_align_items_desktop":"flex-start","same_as_desktop":true,"layout_flex_direction_mobile":"row","layout_gap_mobile":20,"layout_flex_wrap_mobile":"nowrap","layout_flex_justify_mobile":"flex-start","layout_flex_align_items_mobile":"flex-start","layout_grid_columns_mobile":1,"padding_top":50,"padding_bottom":50,"margin_top":0,"margin_bottom":0,"additional_class":""}},"comparison_table_xRw3mt":{"type":"comparison-table","blocks":{"comparison_table_row_mB4Ncx":{"type":"_comparison-table-row","name":"t:row","settings":{},"blocks":{"comparison_table_data_xQNaCV":{"type":"_comparison-table-data","name":"t:cell","settings":{},"blocks":{}},"comparison_table_data_T4jRzT":{"type":"_comparison-table-data","name":"t:cell","settings":{},"blocks":{"text_qDDkxY":{"type":"text","name":"t:title","settings":{"show_on_display":"desktop_and_mobile","text":"<p>MediGel Nail Strip<\/p>","text_style":"h6","paragraph_font_size":"normal","font_weight":400,"alignment":"center","alignment_mobile":"center","show_read_more":false,"read_more_length":50,"read_more_text":"Show more","read_less_text":"Show less","truncate":false,"truncate_length":2,"margin_top":0,"margin_bottom":0,"additional_class":""},"blocks":{}},"logo_BqeXKg":{"type":"logo","name":"t:logo","disabled":true,"settings":{"show_on_display":"desktop_and_mobile","logo_height":25,"inverse":false,"activate_link":true,"margin_top":0,"margin_bottom":0,"additional_class":""},"blocks":{}}},"block_order":["text_qDDkxY","logo_BqeXKg"]},"comparison_table_data_3xUR7P":{"type":"_comparison-table-data","name":"t:cell","settings":{},"blocks":{"text_YaUkW9":{"type":"text","name":"t:text","settings":{"show_on_display":"desktop_and_mobile","text":"<p>Nail strips classiques<\/p>","text_style":"paragraph","paragraph_font_size":"normal","font_weight":400,"alignment":"center","alignment_mobile":"center","show_read_more":false,"read_more_length":200,"read_more_text":"Voir plus","read_less_text":"Voir moins","truncate":false,"truncate_length":2,"margin_top":0,"margin_bottom":0,"additional_class":""},"blocks":{}}},"block_order":["text_YaUkW9"]}},"block_order":["comparison_table_data_xQNaCV","comparison_table_data_T4jRzT","comparison_table_data_3xUR7P"]},"comparison_table_row_DTAALp":{"type":"_comparison-table-row","name":"t:row","settings":{},"blocks":{"comparison_table_data_jdEd7T":{"type":"_comparison-table-data","name":"t:cell","settings":{},"blocks":{"text_HRVqy9":{"type":"text","name":"t:text","settings":{"show_on_display":"desktop_and_mobile","text":"<p>Vernis gel avec des designs variés et innovants<\/p>","text_style":"paragraph","paragraph_font_size":"normal","font_weight":400,"alignment":"left","alignment_mobile":"left","show_read_more":false,"read_more_length":50,"read_more_text":"Voir plus","read_less_text":"Voir moins","truncate":false,"truncate_length":2,"margin_top":0,"margin_bottom":0,"additional_class":""},"blocks":{}}},"block_order":["text_HRVqy9"]},"comparison_table_data_YFb8q7":{"type":"_comparison-table-data","name":"t:cell","settings":{},"blocks":{"icon_HkBLDH":{"type":"icon","name":"t:icon","settings":{"show_on_display":"desktop_and_mobile","icon_type":"icon","icon":"check","icon_custom":"","icon_size":32,"additional_class":""},"blocks":{}}},"block_order":["icon_HkBLDH"]},"comparison_table_data_qBtxMG":{"type":"_comparison-table-data","name":"t:cell","settings":{},"blocks":{"icon_EAqjGU":{"type":"icon","name":"t:icon","settings":{"show_on_display":"desktop_and_mobile","icon_type":"icon","icon":"check","icon_custom":"","icon_size":32,"additional_class":""},"blocks":{}}},"block_order":["icon_EAqjGU"]}},"block_order":["comparison_table_data_jdEd7T","comparison_table_data_YFb8q7","comparison_table_data_qBtxMG"]},"comparison_table_row_gFGtrE":{"type":"_comparison-table-row","name":"t:row","settings":{},"blocks":{"comparison_table_data_PbxQcr":{"type":"_comparison-table-data","name":"t:cell","settings":{},"blocks":{"text_MABrW7":{"type":"text","name":"t:text","settings":{"show_on_display":"desktop_and_mobile","text":"<p>Répare les ongles pendant le port<\/p>","text_style":"paragraph","paragraph_font_size":"normal","font_weight":400,"alignment":"left","alignment_mobile":"left","show_read_more":false,"read_more_length":200,"read_more_text":"Voir plus","read_less_text":"Voir moins","truncate":false,"truncate_length":2,"margin_top":0,"margin_bottom":0,"additional_class":""},"blocks":{}}},"block_order":["text_MABrW7"]},"comparison_table_data_4yMp7M":{"type":"_comparison-table-data","name":"t:cell","settings":{},"blocks":{"icon_RfnqDM":{"type":"icon","name":"t:icon","settings":{"show_on_display":"desktop_and_mobile","icon_type":"icon","icon":"check","icon_custom":"","icon_size":32,"additional_class":""},"blocks":{}}},"block_order":["icon_RfnqDM"]},"comparison_table_data_cMNeg7":{"type":"_comparison-table-data","name":"t:cell","settings":{},"blocks":{"icon_mQUyTj":{"type":"icon","name":"t:icon","settings":{"show_on_display":"desktop_and_mobile","icon_type":"icon","icon":"close","icon_custom":"","icon_size":32,"additional_class":""},"blocks":{}}},"block_order":["icon_mQUyTj"]}},"block_order":["comparison_table_data_PbxQcr","comparison_table_data_4yMp7M","comparison_table_data_cMNeg7"]},"comparison_table_row_QGyXXb":{"type":"_comparison-table-row","name":"t:row","settings":{},"blocks":{"comparison_table_data_3d8UAi":{"type":"_comparison-table-data","name":"t:cell","settings":{},"blocks":{"text_PxjeAp":{"type":"text","name":"t:text","settings":{"show_on_display":"desktop_and_mobile","text":"<p>Technologie Hydrocolloid + Kératine brevetée<\/p>","text_style":"paragraph","paragraph_font_size":"normal","font_weight":400,"alignment":"left","alignment_mobile":"left","show_read_more":false,"read_more_length":200,"read_more_text":"Voir plus","read_less_text":"Voir moins","truncate":false,"truncate_length":2,"margin_top":0,"margin_bottom":0,"additional_class":""},"blocks":{}}},"block_order":["text_PxjeAp"]},"comparison_table_data_BwYUqd":{"type":"_comparison-table-data","name":"t:cell","settings":{},"blocks":{"icon_PijDVM":{"type":"icon","name":"t:icon","settings":{"show_on_display":"desktop_and_mobile","icon_type":"icon","icon":"check","icon_custom":"","icon_size":32,"additional_class":""},"blocks":{}}},"block_order":["icon_PijDVM"]},"comparison_table_data_FmMjGb":{"type":"_comparison-table-data","name":"t:cell","settings":{},"blocks":{"icon_zqiMyi":{"type":"icon","name":"t:icon","settings":{"show_on_display":"desktop_and_mobile","icon_type":"icon","icon":"close","icon_custom":"","icon_size":32,"additional_class":""},"blocks":{}}},"block_order":["icon_zqiMyi"]}},"block_order":["comparison_table_data_3d8UAi","comparison_table_data_BwYUqd","comparison_table_data_FmMjGb"]},"comparison_table_row_caG34e":{"type":"_comparison-table-row","name":"t:row","settings":{},"blocks":{"comparison_table_data_PgrGTJ":{"type":"_comparison-table-data","name":"t:cell","settings":{},"blocks":{"text_ir4RJd":{"type":"text","name":"t:text","settings":{"show_on_display":"desktop_and_mobile","text":"<p>Sans UV, sans lampe, sans matériel<\/p>","text_style":"paragraph","paragraph_font_size":"normal","font_weight":400,"alignment":"left","alignment_mobile":"left","show_read_more":false,"read_more_length":200,"read_more_text":"Voir plus","read_less_text":"Voir moins","truncate":false,"truncate_length":2,"margin_top":0,"margin_bottom":0,"additional_class":""},"blocks":{}}},"block_order":["text_ir4RJd"]},"comparison_table_data_9A7pyk":{"type":"_comparison-table-data","name":"t:cell","settings":{},"blocks":{"icon_7KUkRj":{"type":"icon","name":"t:icon","settings":{"show_on_display":"desktop_and_mobile","icon_type":"icon","icon":"check","icon_custom":"","icon_size":32,"additional_class":""},"blocks":{}}},"block_order":["icon_7KUkRj"]},"comparison_table_data_bkfyAe":{"type":"_comparison-table-data","name":"t:cell","settings":{},"blocks":{"icon_Q74RBV":{"type":"icon","name":"t:icon","settings":{"show_on_display":"desktop_and_mobile","icon_type":"icon","icon":"close","icon_custom":"","icon_size":32,"additional_class":""},"blocks":{}}},"block_order":["icon_Q74RBV"]}},"block_order":["comparison_table_data_PgrGTJ","comparison_table_data_9A7pyk","comparison_table_data_bkfyAe"]},"comparison_table_row_b6V9LV":{"type":"_comparison-table-row","name":"t:row","settings":{},"blocks":{"comparison_table_data_bQEMBE":{"type":"_comparison-table-data","name":"t:cell","settings":{},"blocks":{"text_HcAem4":{"type":"text","name":"t:text","settings":{"show_on_display":"desktop_and_mobile","text":"<p>Cliniquement testé<\/p>","text_style":"paragraph","paragraph_font_size":"normal","font_weight":400,"alignment":"left","alignment_mobile":"left","show_read_more":false,"read_more_length":200,"read_more_text":"Voir plus","read_less_text":"Voir moins","truncate":false,"truncate_length":2,"margin_top":0,"margin_bottom":0,"additional_class":""},"blocks":{}}},"block_order":["text_HcAem4"]},"comparison_table_data_7nbKHy":{"type":"_comparison-table-data","name":"t:cell","settings":{},"blocks":{"icon_Naq3pc":{"type":"icon","name":"t:icon","settings":{"show_on_display":"desktop_and_mobile","icon_type":"icon","icon":"check","icon_custom":"","icon_size":32,"additional_class":""},"blocks":{}}},"block_order":["icon_Naq3pc"]},"comparison_table_data_iYPEwQ":{"type":"_comparison-table-data","name":"t:cell","settings":{},"blocks":{"icon_UY6k49":{"type":"icon","name":"t:icon","settings":{"show_on_display":"desktop_and_mobile","icon_type":"icon","icon":"close","icon_custom":"","icon_size":32,"additional_class":""},"blocks":{}}},"block_order":["icon_UY6k49"]}},"block_order":["comparison_table_data_bQEMBE","comparison_table_data_7nbKHy","comparison_table_data_iYPEwQ"]},"comparison_table_row_4tHYXw":{"type":"_comparison-table-row","name":"t:row","settings":{},"blocks":{"comparison_table_data_zHQ9aA":{"type":"_comparison-table-data","name":"t:cell","settings":{},"blocks":{"text_7krNTE":{"type":"text","name":"t:text","settings":{"show_on_display":"desktop_and_mobile","text":"<p>Fabriqué en Corée <\/p>","text_style":"paragraph","paragraph_font_size":"normal","font_weight":400,"alignment":"left","alignment_mobile":"left","show_read_more":false,"read_more_length":200,"read_more_text":"Voir plus","read_less_text":"Voir moins","truncate":false,"truncate_length":2,"margin_top":0,"margin_bottom":0,"additional_class":""},"blocks":{}}},"block_order":["text_7krNTE"]},"comparison_table_data_xpAbed":{"type":"_comparison-table-data","name":"t:cell","settings":{},"blocks":{"icon_V44yac":{"type":"icon","name":"t:icon","settings":{"show_on_display":"desktop_and_mobile","icon_type":"icon","icon":"check","icon_custom":"","icon_size":32,"additional_class":""},"blocks":{}}},"block_order":["icon_V44yac"]},"comparison_table_data_eUdWgE":{"type":"_comparison-table-data","name":"t:cell","settings":{},"blocks":{"icon_BFgVXt":{"type":"icon","name":"t:icon","settings":{"show_on_display":"desktop_and_mobile","icon_type":"icon","icon":"close","icon_custom":"","icon_size":32,"additional_class":""},"blocks":{}}},"block_order":["icon_BFgVXt"]}},"block_order":["comparison_table_data_zHQ9aA","comparison_table_data_xpAbed","comparison_table_data_eUdWgE"]},"title":{"type":"text","static":true,"settings":{"show_on_display":"desktop_and_mobile","text":"<h3>Pourquoi choisir nos produits ?<\/h3>","text_style":"h3","paragraph_font_size":"normal","font_weight":400,"alignment":"center","alignment_mobile":"center","show_read_more":false,"read_more_length":200,"read_more_text":"Voir plus","read_less_text":"Voir moins","truncate":false,"truncate_length":2,"margin_top":0,"margin_bottom":40,"additional_class":""},"blocks":{}}},"block_order":["comparison_table_row_mB4Ncx","comparison_table_row_DTAALp","comparison_table_row_gFGtrE","comparison_table_row_QGyXXb","comparison_table_row_caG34e","comparison_table_row_b6V9LV","comparison_table_row_4tHYXw"],"name":"t:comparison_table","settings":{"show_on_display":"desktop_and_mobile","section_width":"narrow","color_scheme":"scheme-1","color_scheme_table":"scheme-1","cell_min_width_mobile":120,"highlighted_column":2,"color_highlighted_column":"#000000","color_highlighted_background_column":"#ffffff","padding_top":50,"padding_bottom":50,"margin_top":0,"margin_bottom":0,"additional_class":""}},"custom_section_jGbBhQ":{"type":"custom-section","blocks":{"image_bfajhe":{"type":"image","name":"t:image","settings":{"show_on_display":"desktop_and_mobile","image":"shopify:\/\/shop_images\/Manucure_sans_bavure_7.png","show_placeholder":true,"link":"","image_ratio":"square","image_width_desktop":100,"image_width_mobile":100,"additional_class":""},"blocks":{}},"group_JJHQXe":{"type":"group","name":"t:group","settings":{"show_on_display":"desktop_and_mobile","wrap_in_card":false,"color_scheme":"scheme-2","show_card_border":false,"layout_type":"flex","width_desktop":100,"layout_direction_desktop":"column","layout_grid_columns_desktop":3,"layout_gap_desktop":15,"layout_wrap_desktop":"nowrap","layout_justify_desktop":"flex-start","layout_align_items_desktop":"flex-start","same_as_desktop":true,"width_mobile":100,"layout_direction_mobile":"column","layout_grid_columns_mobile":1,"layout_gap_mobile":10,"layout_wrap_mobile":"nowrap","layout_justify_mobile":"flex-start","layout_align_items_mobile":"flex-start","use_global_container_padding":true,"padding_horizontal":30,"padding_vertical":30,"margin_top":10,"margin_bottom":10,"additional_class":""},"blocks":{"text_eRYL6y":{"type":"text","name":"t:title","settings":{"show_on_display":"desktop_and_mobile","text":"<p>Vous méritez des ongles beaux ET en bonne santé. Enfin, vous n'avez plus à choisir.<\/p>","text_style":"h3","paragraph_font_size":"normal","font_weight":400,"alignment":"left","alignment_mobile":"left","show_read_more":false,"read_more_length":200,"read_more_text":"Voir plus","read_less_text":"Voir moins","truncate":false,"truncate_length":2,"margin_top":0,"margin_bottom":0,"additional_class":""},"blocks":{}},"text_MTxF8j":{"type":"text","name":"t:text","settings":{"show_on_display":"desktop_and_mobile","text":"<p>Le MediGel Nail Strip n'est pas une simple bande en gel. C'est une innovation K-Beauty qui délivre des actifs réparateurs directement sur la plaque de votre ongle — 24h\/24, pendant toute la durée du port. Résultat : à chaque pose, vos ongles récupèrent, se renforcent et retrouvent leur éclat naturel.<\/p>","text_style":"paragraph","paragraph_font_size":"normal","font_weight":400,"alignment":"left","alignment_mobile":"left","show_read_more":false,"read_more_length":200,"read_more_text":"Voir plus","read_less_text":"Voir moins","truncate":false,"truncate_length":2,"margin_top":0,"margin_bottom":0,"additional_class":""},"blocks":{}},"accordions_3WTbFR":{"type":"accordions","name":"t:accordions","settings":{"show_on_display":"desktop_and_mobile","icon":"caret","dividers":true,"additional_class":""},"blocks":{"accordion_p4yiUY":{"type":"_accordion","settings":{"show_on_display":"desktop_and_mobile","heading":"Réparation active","open_by_default":false,"icon":"none","icon_custom":"","additional_class":""},"blocks":{"text_8LxUtB":{"type":"text","settings":{"show_on_display":"desktop_and_mobile","text":"<p>La couche Hydrocolloid en contact direct avec votre ongle maintient l'hydratation et libère progressivement la Kératine. Idéal après des années de gel, d'acrylique ou d'acétone. Vos ongles ne sont plus seulement couverts — ils guérissent.<\/p>","text_style":"paragraph","paragraph_font_size":"normal","font_weight":400,"alignment":"left","alignment_mobile":"left","show_read_more":false,"read_more_length":100,"read_more_text":"Voir plus","read_less_text":"Voir moins","truncate":false,"truncate_length":2,"margin_top":0,"margin_bottom":0,"additional_class":""},"blocks":{}}},"block_order":["text_8LxUtB"]},"accordion_79Ewap":{"type":"_accordion","settings":{"show_on_display":"desktop_and_mobile","heading":"Beauté professionnelle","open_by_default":false,"icon":"none","icon_custom":"","additional_class":""},"blocks":{"text_zjc8Uc":{"type":"text","settings":{"show_on_display":"desktop_and_mobile","text":"<p>Grâce à la couche gel haute brillance en surface, le MediGel offre un volume et un éclat comparables à une pose en institut. Aucune lampe UV, aucun matériel, aucun rendez-vous. Posez vos strips en 5 minutes, et le résultat parle de lui-même.<\/p>","text_style":"paragraph","paragraph_font_size":"normal","font_weight":400,"alignment":"left","alignment_mobile":"left","show_read_more":false,"read_more_length":100,"read_more_text":"Voir plus","read_less_text":"Voir moins","truncate":false,"truncate_length":2,"margin_top":0,"margin_bottom":0,"additional_class":""},"blocks":{}}},"block_order":["text_zjc8Uc"]},"accordion_zWrfzX":{"type":"_accordion","settings":{"show_on_display":"desktop_and_mobile","heading":"Sécurité & douceur","open_by_default":false,"icon":"none","icon_custom":"","additional_class":""},"blocks":{"text_YyUMWd":{"type":"text","settings":{"show_on_display":"desktop_and_mobile","text":"<p>Une étude clinique contrôlée menée sur 21 participantes pendant 14 jours confirme : réduction mesurable de la rugosité des ongles, aucune réaction allergique, aucune irritation. Et 100% des participantes ont dit qu'elles le recommanderaient. Ce n'est pas du marketing, c'est de la science!<\/p>","text_style":"paragraph","paragraph_font_size":"normal","font_weight":400,"alignment":"left","alignment_mobile":"left","show_read_more":false,"read_more_length":100,"read_more_text":"Voir plus","read_less_text":"Voir moins","truncate":false,"truncate_length":2,"margin_top":0,"margin_bottom":0,"additional_class":""},"blocks":{}}},"block_order":["text_YyUMWd"]}},"block_order":["accordion_p4yiUY","accordion_79Ewap","accordion_zWrfzX"]},"review_CJeXtq":{"type":"review","name":"t:review_display_2","settings":{"show_on_display":"desktop_and_mobile","display_type":"2","wrap_in_card":true,"color_scheme":"scheme-2","show_card_border":true,"rating":4.5,"image_ratio":"landscape","source":"uploaded","video_url":"","title":"Excellent produit !","content":"<p>J'avais les ongles complètement détruits après des années de gel en institut. Au bout de 2 semaines avec le MediGel, ils sont plus lisses et moins cassants. Et le rendu est vraiment beau, pas cheap du tout.<\/p>","author":"Marine L.","date":"Le 14\/02\/2026","margin_top":10,"margin_bottom":0,"additional_class":""},"blocks":{}}},"block_order":["text_eRYL6y","text_MTxF8j","accordions_3WTbFR","review_CJeXtq"]}},"block_order":["image_bfajhe","group_JJHQXe"],"name":"t:image_with_text","settings":{"show_on_display":"desktop_and_mobile","section_width":"normal","color_scheme":"scheme-1","wrap_in_card":false,"color_scheme_card":"","layout_type":"flex","layout_flex_direction_desktop":"row","layout_grid_columns_desktop":3,"layout_gap_desktop":50,"layout_flex_wrap_desktop":"nowrap","layout_flex_justify_desktop":"flex-start","layout_flex_align_items_desktop":"center","same_as_desktop":false,"layout_flex_direction_mobile":"column","layout_gap_mobile":10,"layout_flex_wrap_mobile":"nowrap","layout_flex_justify_mobile":"flex-start","layout_flex_align_items_mobile":"flex-start","layout_grid_columns_mobile":1,"padding_top":50,"padding_bottom":100,"margin_top":0,"margin_bottom":0,"additional_class":""}},"custom_section_Ng8LAT":{"type":"custom-section","blocks":{"text_3bbfVM":{"type":"text","name":"t:title","settings":{"show_on_display":"desktop_and_mobile","text":"<h1>Ingrédients<\/h1>","text_style":"h3","paragraph_font_size":"normal","font_weight":400,"alignment":"left","alignment_mobile":"left","show_read_more":false,"read_more_length":100,"read_more_text":"Voir plus","read_less_text":"Voir moins","truncate":false,"truncate_length":2,"margin_top":0,"margin_bottom":0,"additional_class":""},"blocks":{}},"slider_cVdH83":{"type":"slider","name":"t:slider","settings":{"show_on_display":"desktop_and_mobile","per_page_desktop":4,"per_page_mobile":"1.8","gap":15,"show_arrows":true,"show_pagination":false,"rewind":false,"autoplay":false,"autoplay_speed":4,"margin_top":0,"margin_bottom":0,"additional_class":""},"blocks":{"slide_NTK3td":{"type":"_slide","name":"t:slide","settings":{"show_on_display":"desktop_and_mobile","wrap_in_card":false,"color_scheme":"","layout_direction":"row","layout_wrap":"nowrap","layout_gap":10,"layout_justify":"flex-start","layout_align_items":"flex-start","margin_top":0,"margin_bottom":0,"additional_class":""},"blocks":{"group_mDfHam":{"type":"group","name":"t:group","settings":{"show_on_display":"desktop_and_mobile","wrap_in_card":true,"color_scheme":"scheme-2","show_card_border":true,"layout_type":"flex","width_desktop":100,"layout_direction_desktop":"column","layout_grid_columns_desktop":3,"layout_gap_desktop":10,"layout_wrap_desktop":"nowrap","layout_justify_desktop":"flex-start","layout_align_items_desktop":"flex-start","same_as_desktop":true,"width_mobile":100,"layout_direction_mobile":"column","layout_grid_columns_mobile":1,"layout_gap_mobile":10,"layout_wrap_mobile":"nowrap","layout_justify_mobile":"flex-start","layout_align_items_mobile":"flex-start","use_global_container_padding":true,"padding_horizontal":30,"padding_vertical":30,"margin_top":0,"margin_bottom":0,"additional_class":""},"blocks":{"image_6TKwmB":{"type":"image","name":"t:image","disabled":true,"settings":{"show_on_display":"desktop_and_mobile","image":"shopify:\/\/shop_images\/Manucure_sans_bavure_10.png","show_placeholder":true,"link":"","image_ratio":"adapt","image_width_desktop":100,"image_width_mobile":100,"additional_class":""},"blocks":{}},"text_BQgPtX":{"type":"text","name":"t:text","settings":{"show_on_display":"desktop_and_mobile","text":"<p>Kératine<\/p>","text_style":"h6","paragraph_font_size":"normal","font_weight":400,"alignment":"left","alignment_mobile":"left","show_read_more":false,"read_more_length":100,"read_more_text":"Voir plus","read_less_text":"Voir moins","truncate":false,"truncate_length":2,"margin_top":0,"margin_bottom":0,"additional_class":""},"blocks":{}},"text_KgqxkK":{"type":"text","name":"t:text","settings":{"show_on_display":"desktop_and_mobile","text":"<p>La protéine structurelle de l'ongle. Reconstitue la fibre de l'ongle fragilisée et renforce sa résistance à la casse.<\/p><p><em><strong>Ongles réparés & renforcés<\/strong><\/em><\/p>","text_style":"paragraph","paragraph_font_size":"normal","font_weight":400,"alignment":"left","alignment_mobile":"left","show_read_more":false,"read_more_length":100,"read_more_text":"Voir plus","read_less_text":"Voir moins","truncate":false,"truncate_length":2,"margin_top":0,"margin_bottom":0,"additional_class":""},"blocks":{}}},"block_order":["image_6TKwmB","text_BQgPtX","text_KgqxkK"]}},"block_order":["group_mDfHam"]},"slide_cjqwc9":{"type":"_slide","name":"t:slide","settings":{"show_on_display":"desktop_and_mobile","wrap_in_card":false,"color_scheme":"","layout_direction":"row","layout_wrap":"nowrap","layout_gap":10,"layout_justify":"flex-start","layout_align_items":"flex-start","margin_top":0,"margin_bottom":0,"additional_class":""},"blocks":{"group_cAzqPQ":{"type":"group","name":"t:group","settings":{"show_on_display":"desktop_and_mobile","wrap_in_card":true,"color_scheme":"scheme-2","show_card_border":true,"layout_type":"flex","width_desktop":100,"layout_direction_desktop":"column","layout_grid_columns_desktop":3,"layout_gap_desktop":10,"layout_wrap_desktop":"nowrap","layout_justify_desktop":"flex-start","layout_align_items_desktop":"flex-start","same_as_desktop":true,"width_mobile":100,"layout_direction_mobile":"column","layout_grid_columns_mobile":1,"layout_gap_mobile":10,"layout_wrap_mobile":"nowrap","layout_justify_mobile":"flex-start","layout_align_items_mobile":"flex-start","use_global_container_padding":true,"padding_horizontal":30,"padding_vertical":30,"margin_top":0,"margin_bottom":0,"additional_class":""},"blocks":{"image_xHeMAE":{"type":"image","name":"t:image","disabled":true,"settings":{"show_on_display":"desktop_and_mobile","image":"shopify:\/\/shop_images\/Manucure_sans_bavure_6.png","show_placeholder":true,"link":"","image_ratio":"adapt","image_width_desktop":100,"image_width_mobile":100,"additional_class":""},"blocks":{}},"text_Eerkxm":{"type":"text","name":"t:text","settings":{"show_on_display":"desktop_and_mobile","text":"<p>Hydrocolloid médical<\/p>","text_style":"h6","paragraph_font_size":"normal","font_weight":400,"alignment":"left","alignment_mobile":"left","show_read_more":false,"read_more_length":100,"read_more_text":"Voir plus","read_less_text":"Voir moins","truncate":false,"truncate_length":2,"margin_top":0,"margin_bottom":0,"additional_class":""},"blocks":{}},"text_r6xULh":{"type":"text","name":"t:text","settings":{"show_on_display":"desktop_and_mobile","text":"<p>Technologie empruntée aux pansements cicatrisants. Maintient un environnement hydraté optimal pour la régénération de l'ongle.<\/p><p><em><strong>Hydratation & régénération 24h<\/strong><\/em><\/p>","text_style":"paragraph","paragraph_font_size":"normal","font_weight":400,"alignment":"left","alignment_mobile":"left","show_read_more":false,"read_more_length":100,"read_more_text":"Voir plus","read_less_text":"Voir moins","truncate":false,"truncate_length":2,"margin_top":0,"margin_bottom":0,"additional_class":""},"blocks":{}}},"block_order":["image_xHeMAE","text_Eerkxm","text_r6xULh"]}},"block_order":["group_cAzqPQ"]},"slide_QXj9hd":{"type":"_slide","name":"t:slide","settings":{"show_on_display":"desktop_and_mobile","wrap_in_card":false,"color_scheme":"","layout_direction":"row","layout_wrap":"nowrap","layout_gap":10,"layout_justify":"flex-start","layout_align_items":"flex-start","margin_top":0,"margin_bottom":0,"additional_class":""},"blocks":{"group_njywVW":{"type":"group","name":"t:group","settings":{"show_on_display":"desktop_and_mobile","wrap_in_card":true,"color_scheme":"scheme-2","show_card_border":true,"layout_type":"flex","width_desktop":100,"layout_direction_desktop":"column","layout_grid_columns_desktop":3,"layout_gap_desktop":10,"layout_wrap_desktop":"nowrap","layout_justify_desktop":"flex-start","layout_align_items_desktop":"flex-start","same_as_desktop":true,"width_mobile":100,"layout_direction_mobile":"column","layout_grid_columns_mobile":1,"layout_gap_mobile":10,"layout_wrap_mobile":"nowrap","layout_justify_mobile":"flex-start","layout_align_items_mobile":"flex-start","use_global_container_padding":true,"padding_horizontal":30,"padding_vertical":30,"margin_top":0,"margin_bottom":0,"additional_class":""},"blocks":{"image_HC68eP":{"type":"image","name":"t:image","disabled":true,"settings":{"show_on_display":"desktop_and_mobile","image":"shopify:\/\/shop_images\/Manucure_sans_bavure_9.png","show_placeholder":true,"link":"","image_ratio":"adapt","image_width_desktop":100,"image_width_mobile":100,"additional_class":""},"blocks":{}},"text_3HpAkj":{"type":"text","name":"t:text","settings":{"show_on_display":"desktop_and_mobile","text":"<p>Base PU Fabric<\/p>","text_style":"h6","paragraph_font_size":"normal","font_weight":400,"alignment":"left","alignment_mobile":"left","show_read_more":false,"read_more_length":100,"read_more_text":"Voir plus","read_less_text":"Voir moins","truncate":false,"truncate_length":2,"margin_top":0,"margin_bottom":0,"additional_class":""},"blocks":{}},"text_JbLFbm":{"type":"text","name":"t:text","settings":{"show_on_display":"desktop_and_mobile","text":"<p>Tissu polyuréthane de haute qualité qui garantit une adhérence parfaite, un port confortable et une résistance aux chocs du quotidien.<\/p><p><em><strong>Tenue longue durée & confort<\/strong><\/em><\/p>","text_style":"paragraph","paragraph_font_size":"normal","font_weight":400,"alignment":"left","alignment_mobile":"left","show_read_more":false,"read_more_length":100,"read_more_text":"Voir plus","read_less_text":"Voir moins","truncate":false,"truncate_length":2,"margin_top":0,"margin_bottom":0,"additional_class":""},"blocks":{}}},"block_order":["image_HC68eP","text_3HpAkj","text_JbLFbm"]}},"block_order":["group_njywVW"]},"slide_6UggtP":{"type":"_slide","name":"t:slide","settings":{"show_on_display":"desktop_and_mobile","wrap_in_card":false,"color_scheme":"","layout_direction":"row","layout_wrap":"nowrap","layout_gap":10,"layout_justify":"flex-start","layout_align_items":"flex-start","margin_top":0,"margin_bottom":0,"additional_class":""},"blocks":{"group_BCAUnH":{"type":"group","name":"t:group","settings":{"show_on_display":"desktop_and_mobile","wrap_in_card":true,"color_scheme":"scheme-2","show_card_border":true,"layout_type":"flex","width_desktop":100,"layout_direction_desktop":"column","layout_grid_columns_desktop":3,"layout_gap_desktop":10,"layout_wrap_desktop":"nowrap","layout_justify_desktop":"flex-start","layout_align_items_desktop":"flex-start","same_as_desktop":true,"width_mobile":100,"layout_direction_mobile":"column","layout_grid_columns_mobile":1,"layout_gap_mobile":10,"layout_wrap_mobile":"nowrap","layout_justify_mobile":"flex-start","layout_align_items_mobile":"flex-start","use_global_container_padding":true,"padding_horizontal":30,"padding_vertical":30,"margin_top":0,"margin_bottom":0,"additional_class":""},"blocks":{"image_hebRDa":{"type":"image","name":"t:image","disabled":true,"settings":{"show_on_display":"desktop_and_mobile","image":"shopify:\/\/shop_images\/Manucure_sans_bavure_7.png","show_placeholder":true,"link":"","image_ratio":"adapt","image_width_desktop":100,"image_width_mobile":100,"additional_class":""},"blocks":{}},"text_eBjyXE":{"type":"text","name":"t:text","settings":{"show_on_display":"desktop_and_mobile","text":"<p>Gel coating haute brillance<\/p>","text_style":"h6","paragraph_font_size":"normal","font_weight":400,"alignment":"left","alignment_mobile":"left","show_read_more":false,"read_more_length":100,"read_more_text":"Voir plus","read_less_text":"Voir moins","truncate":false,"truncate_length":2,"margin_top":0,"margin_bottom":0,"additional_class":""},"blocks":{}},"text_gg9zKK":{"type":"text","name":"t:text","settings":{"show_on_display":"desktop_and_mobile","text":"<p>Couche gel volume ultra-brillante qui reproduit l'effet d'un gel en institut — sans lampe UV, sans cabine, sans compromis sur le rendu.<\/p><p><em><strong>Finition gel professionnel à domicile<\/strong><\/em><\/p>","text_style":"paragraph","paragraph_font_size":"normal","font_weight":400,"alignment":"left","alignment_mobile":"left","show_read_more":false,"read_more_length":100,"read_more_text":"Voir plus","read_less_text":"Voir moins","truncate":false,"truncate_length":2,"margin_top":0,"margin_bottom":0,"additional_class":""},"blocks":{}}},"block_order":["image_hebRDa","text_eBjyXE","text_gg9zKK"]}},"block_order":["group_BCAUnH"]}},"block_order":["slide_NTK3td","slide_cjqwc9","slide_QXj9hd","slide_6UggtP"]}},"block_order":["text_3bbfVM","slider_cVdH83"],"name":"t:custom_section","settings":{"show_on_display":"desktop_and_mobile","section_width":"normal","color_scheme":"","wrap_in_card":false,"color_scheme_card":"","layout_type":"flex","layout_flex_direction_desktop":"column","layout_grid_columns_desktop":3,"layout_gap_desktop":20,"layout_flex_wrap_desktop":"nowrap","layout_flex_justify_desktop":"flex-start","layout_flex_align_items_desktop":"flex-start","same_as_desktop":true,"layout_flex_direction_mobile":"column","layout_gap_mobile":20,"layout_flex_wrap_mobile":"nowrap","layout_flex_justify_mobile":"flex-start","layout_flex_align_items_mobile":"flex-start","layout_grid_columns_mobile":1,"padding_top":50,"padding_bottom":50,"margin_top":0,"margin_bottom":0,"additional_class":""}},"custom_section_TDJcGh":{"type":"custom-section","blocks":{"group_L4WMkg":{"type":"group","name":"t:group","settings":{"show_on_display":"desktop_and_mobile","wrap_in_card":false,"color_scheme":"scheme-2","show_card_border":false,"layout_type":"flex","width_desktop":100,"layout_direction_desktop":"column","layout_grid_columns_desktop":3,"layout_gap_desktop":15,"layout_wrap_desktop":"nowrap","layout_justify_desktop":"flex-start","layout_align_items_desktop":"flex-start","same_as_desktop":true,"width_mobile":100,"layout_direction_mobile":"column","layout_grid_columns_mobile":1,"layout_gap_mobile":10,"layout_wrap_mobile":"nowrap","layout_justify_mobile":"flex-start","layout_align_items_mobile":"flex-start","use_global_container_padding":true,"padding_horizontal":30,"padding_vertical":30,"margin_top":10,"margin_bottom":10,"additional_class":""},"blocks":{"text_MBGNKP":{"type":"text","name":"t:title","settings":{"show_on_display":"desktop_and_mobile","text":"<p>Fini les ongles que vous cachez. Place aux ongles dont vous êtes fière.<\/p>","text_style":"h3","paragraph_font_size":"normal","font_weight":400,"alignment":"left","alignment_mobile":"left","show_read_more":false,"read_more_length":200,"read_more_text":"Voir plus","read_less_text":"Voir moins","truncate":false,"truncate_length":2,"margin_top":0,"margin_bottom":0,"additional_class":""},"blocks":{}},"text_Q9qiWi":{"type":"text","name":"t:text","settings":{"show_on_display":"desktop_and_mobile","text":"<p>Les ongles abîmés, ce n'est pas une fatalité. C'est souvent le résultat d'années de poses agressives, de manque de soin, ou simplement d'un quotidien chargé. <\/p><p>Le MediGel Nail Strip est là pour vous : une solution qui ne demande pas de sacrifice entre beauté et santé. <\/p><p><strong>Parce que vos ongles méritent les deux!<\/strong><\/p>","text_style":"paragraph","paragraph_font_size":"normal","font_weight":400,"alignment":"left","alignment_mobile":"left","show_read_more":false,"read_more_length":200,"read_more_text":"Voir plus","read_less_text":"Voir moins","truncate":false,"truncate_length":2,"margin_top":0,"margin_bottom":0,"additional_class":""},"blocks":{}},"button_RzzHkP":{"type":"button","name":"t:button","disabled":true,"settings":{"show_on_display":"desktop_and_mobile","link":"","open_in_new_tab":false,"label":"En savoir plus","button_style":"secondary","button_shape":"default","icon":"open_in_new","icon_custom":"arrow_forward","icon_position":"end","margin_top":0,"margin_bottom":0,"additional_class":""},"blocks":{}}},"block_order":["text_MBGNKP","text_Q9qiWi","button_RzzHkP"]},"before_after_gAbCqR":{"type":"before-after","name":"t:before_after","settings":{"image_before":"shopify:\/\/shop_images\/Manucure_sans_bavure_13.png","image_after":"shopify:\/\/shop_images\/Manucure_sans_bavure_14.png","image_ratio":"adapt","label_before":"Avant","label_after":"Après","label_badge_style":"secondary","default_position":50,"image_width_desktop":100,"image_width_mobile":100,"margin_top":0,"margin_bottom":0,"additional_class":""},"blocks":{}}},"block_order":["group_L4WMkg","before_after_gAbCqR"],"name":"t:image_with_text_reversed","settings":{"show_on_display":"desktop_and_mobile","section_width":"normal","color_scheme":"scheme-1","wrap_in_card":false,"color_scheme_card":"","layout_type":"flex","layout_flex_direction_desktop":"row","layout_grid_columns_desktop":3,"layout_gap_desktop":30,"layout_flex_wrap_desktop":"nowrap","layout_flex_justify_desktop":"flex-start","layout_flex_align_items_desktop":"center","same_as_desktop":false,"layout_flex_direction_mobile":"column","layout_gap_mobile":10,"layout_flex_wrap_mobile":"nowrap","layout_flex_justify_mobile":"flex-start","layout_flex_align_items_mobile":"flex-start","layout_grid_columns_mobile":1,"padding_top":50,"padding_bottom":50,"margin_top":0,"margin_bottom":0,"additional_class":""}},"custom_section_LBJBG7":{"type":"custom-section","blocks":{"group_NkNJJg":{"type":"group","name":"t:group","settings":{"show_on_display":"desktop_and_mobile","wrap_in_card":true,"color_scheme":"scheme-2","show_card_border":false,"layout_type":"flex","width_desktop":55,"layout_direction_desktop":"column","layout_grid_columns_desktop":3,"layout_gap_desktop":10,"layout_wrap_desktop":"nowrap","layout_justify_desktop":"center","layout_align_items_desktop":"center","same_as_desktop":false,"width_mobile":100,"layout_direction_mobile":"column","layout_grid_columns_mobile":1,"layout_gap_mobile":10,"layout_wrap_mobile":"nowrap","layout_justify_mobile":"flex-start","layout_align_items_mobile":"flex-start","use_global_container_padding":false,"padding_horizontal":20,"padding_vertical":30,"margin_top":0,"margin_bottom":0,"additional_class":""},"blocks":{"text_VLtRib":{"type":"text","name":"t:title","settings":{"show_on_display":"desktop_and_mobile","text":"<h4>Besoin d'aide ?<\/h4>","text_style":"h5","paragraph_font_size":"normal","font_weight":400,"alignment":"center","alignment_mobile":"left","show_read_more":false,"read_more_length":100,"read_more_text":"Voir plus","read_less_text":"Voir moins","truncate":false,"truncate_length":2,"margin_top":0,"margin_bottom":0,"additional_class":""},"blocks":{}},"text_FyFaMj":{"type":"text","name":"t:text","settings":{"show_on_display":"desktop_and_mobile","text":"<p>Notre équipe est là pour vous répondre du Lundi au Vendredi de 8h30 à 19h. Samedi de 10h à 17h.<\/p>","text_style":"paragraph","paragraph_font_size":"normal","font_weight":400,"alignment":"center","alignment_mobile":"left","show_read_more":false,"read_more_length":100,"read_more_text":"Voir plus","read_less_text":"Voir moins","truncate":false,"truncate_length":2,"margin_top":0,"margin_bottom":20,"additional_class":""},"blocks":{}},"button_Q3UxFk":{"type":"button","name":"t:button","settings":{"show_on_display":"desktop_and_mobile","link":"shopify:\/\/pages\/contact","open_in_new_tab":false,"label":"Contactez notre support","button_style":"primary","button_shape":"full-width","icon":"none","icon_custom":"","icon_position":"end","margin_top":0,"margin_bottom":0,"additional_class":""},"blocks":{}},"button_qUpbgY":{"type":"button","name":"t:button","settings":{"show_on_display":"desktop_and_mobile","link":"shopify:\/\/pages\/contact","open_in_new_tab":false,"label":"Consultez notre aide","button_style":"secondary","button_shape":"full-width","icon":"none","icon_custom":"","icon_position":"end","margin_top":0,"margin_bottom":0,"additional_class":""},"blocks":{}}},"block_order":["text_VLtRib","text_FyFaMj","button_Q3UxFk","button_qUpbgY"]},"group_ampbiX":{"type":"group","name":"t:group","settings":{"show_on_display":"desktop_and_mobile","wrap_in_card":false,"color_scheme":"","show_card_border":false,"layout_type":"flex","width_desktop":100,"layout_direction_desktop":"column","layout_grid_columns_desktop":3,"layout_gap_desktop":10,"layout_wrap_desktop":"nowrap","layout_justify_desktop":"flex-start","layout_align_items_desktop":"flex-start","same_as_desktop":true,"width_mobile":100,"layout_direction_mobile":"column","layout_grid_columns_mobile":1,"layout_gap_mobile":10,"layout_wrap_mobile":"nowrap","layout_justify_mobile":"flex-start","layout_align_items_mobile":"flex-start","use_global_container_padding":true,"padding_horizontal":30,"padding_vertical":30,"margin_top":0,"margin_bottom":0,"additional_class":""},"blocks":{"text_XR3Gyx":{"type":"text","name":"t:title","settings":{"show_on_display":"desktop_and_mobile","text":"<h3>Questions fréquentes<\/h3>","text_style":"h3","paragraph_font_size":"normal","font_weight":400,"alignment":"left","alignment_mobile":"left","show_read_more":false,"read_more_length":100,"read_more_text":"Voir plus","read_less_text":"Voir moins","truncate":false,"truncate_length":2,"margin_top":0,"margin_bottom":10,"additional_class":""},"blocks":{}},"accordions_nr9je8":{"type":"accordions","name":"t:accordions","settings":{"show_on_display":"desktop_and_mobile","icon":"caret","dividers":true,"additional_class":""},"blocks":{"accordion_JqmDtF":{"type":"_accordion","settings":{"show_on_display":"desktop_and_mobile","heading":"Combien de temps les strips tiennent-ils ?","open_by_default":false,"icon":"none","icon_custom":"","additional_class":""},"blocks":{"text_VgC4hW":{"type":"text","settings":{"show_on_display":"desktop_and_mobile","text":"<p>Jusqu'à 14 jours selon votre activité et votre exposition à l'eau. Pour une tenue maximale, évitez tout contact avec l'eau dans les 4 premières heures après la pose.<\/p>","text_style":"paragraph","paragraph_font_size":"normal","font_weight":400,"alignment":"left","alignment_mobile":"left","show_read_more":false,"read_more_length":100,"read_more_text":"Voir plus","read_less_text":"Voir moins","truncate":false,"truncate_length":2,"margin_top":0,"margin_bottom":0,"additional_class":""},"blocks":{}}},"block_order":["text_VgC4hW"]},"accordion_cmFMRU":{"type":"_accordion","settings":{"show_on_display":"desktop_and_mobile","heading":"Comment retirer les strips sans abîmer mes ongles ?","open_by_default":false,"icon":"none","icon_custom":"","additional_class":""},"blocks":{"text_RTRkL8":{"type":"text","settings":{"show_on_display":"desktop_and_mobile","text":"<p>Décollez doucement depuis le bord libre de l'ongle. Aucun acétone, aucune lime. Le retrait est propre, rapide et sans agression.<\/p>","text_style":"paragraph","paragraph_font_size":"normal","font_weight":400,"alignment":"left","alignment_mobile":"left","show_read_more":false,"read_more_length":100,"read_more_text":"Voir plus","read_less_text":"Voir moins","truncate":false,"truncate_length":2,"margin_top":0,"margin_bottom":0,"additional_class":""},"blocks":{}}},"block_order":["text_RTRkL8"]},"accordion_nXcLbm":{"type":"_accordion","settings":{"show_on_display":"desktop_and_mobile","heading":"Ce produit convient-il aux ongles très abîmés ?","open_by_default":false,"icon":"none","icon_custom":"","additional_class":""},"blocks":{"text_GNNJ8d":{"type":"text","settings":{"show_on_display":"desktop_and_mobile","text":"<p>C'est précisément pour ça qu'il a été conçu. La couche Hydrocolloid + Kératine est particulièrement bénéfique pour les ongles fragilisés après des poses gel ou acrylique répétées.<\/p>","text_style":"paragraph","paragraph_font_size":"normal","font_weight":400,"alignment":"left","alignment_mobile":"left","show_read_more":false,"read_more_length":100,"read_more_text":"Voir plus","read_less_text":"Voir moins","truncate":false,"truncate_length":2,"margin_top":0,"margin_bottom":0,"additional_class":""},"blocks":{}}},"block_order":["text_GNNJ8d"]},"accordion_aCGBQK":{"type":"_accordion","settings":{"show_on_display":"desktop_and_mobile","heading":"Faut-il une lampe UV ?","open_by_default":false,"icon":"none","icon_custom":"","additional_class":""},"blocks":{"text_7PLUjc":{"type":"text","settings":{"show_on_display":"desktop_and_mobile","text":"<p>Non. Aucune lampe, aucun matériel supplémentaire. Juste vos mains et les strips fournis dans le kit.<\/p>","text_style":"paragraph","paragraph_font_size":"normal","font_weight":400,"alignment":"left","alignment_mobile":"left","show_read_more":false,"read_more_length":100,"read_more_text":"Voir plus","read_less_text":"Voir moins","truncate":false,"truncate_length":2,"margin_top":0,"margin_bottom":0,"additional_class":""},"blocks":{}}},"block_order":["text_7PLUjc"]},"accordion_MwdLtn":{"type":"_accordion","settings":{"show_on_display":"desktop_and_mobile","heading":"Le produit est-il adapté aux peaux sensibles ?","open_by_default":false,"icon":"none","icon_custom":"","additional_class":""},"blocks":{"text_V3FkqV":{"type":"text","settings":{"show_on_display":"desktop_and_mobile","text":"<p>Oui. L'étude clinique menée sur 21 participantes n'a détecté aucune réaction cutanée ni dermatite de contact. Le produit est confirmé dermatologiquement sûr.<\/p>","text_style":"paragraph","paragraph_font_size":"normal","font_weight":400,"alignment":"left","alignment_mobile":"left","show_read_more":false,"read_more_length":100,"read_more_text":"Voir plus","read_less_text":"Voir moins","truncate":false,"truncate_length":2,"margin_top":0,"margin_bottom":0,"additional_class":""},"blocks":{}}},"block_order":["text_V3FkqV"]}},"block_order":["accordion_JqmDtF","accordion_cmFMRU","accordion_nXcLbm","accordion_aCGBQK","accordion_MwdLtn"]}},"block_order":["text_XR3Gyx","accordions_nr9je8"]}},"block_order":["group_NkNJJg","group_ampbiX"],"name":"t:faq_2","settings":{"show_on_display":"desktop_and_mobile","section_width":"normal","color_scheme":"scheme-1","wrap_in_card":false,"color_scheme_card":"","layout_type":"flex","layout_flex_direction_desktop":"row","layout_grid_columns_desktop":3,"layout_gap_desktop":50,"layout_flex_wrap_desktop":"nowrap","layout_flex_justify_desktop":"flex-start","layout_flex_align_items_desktop":"flex-start","same_as_desktop":false,"layout_flex_direction_mobile":"column-reverse","layout_gap_mobile":20,"layout_flex_wrap_mobile":"nowrap","layout_flex_justify_mobile":"flex-start","layout_flex_align_items_mobile":"flex-start","layout_grid_columns_mobile":1,"padding_top":75,"padding_bottom":75,"margin_top":0,"margin_bottom":0,"additional_class":""}},"reviews_8P6xW3":{"type":"reviews","blocks":{"review_slide_k9DNXe":{"type":"_review-slide","name":"t:review_display_2","settings":{"show_on_display":"desktop_and_mobile","display_type":"2","wrap_in_card":true,"color_scheme":"scheme-2","show_card_border":true,"rating":4.5,"image_ratio":"landscape","source":"uploaded","video_url":"","title":"Excellent produit !","content":"<p>Écrivez un retour à propos de vos produits. Ajustez le nombre de colonnes en fonction de la taille moyenne des messages.<\/p>","author":"John Doe","date":"Le 11\/03\/2025","margin_top":0,"margin_bottom":0,"additional_class":""},"blocks":{}},"review_slide_M9WWkF":{"type":"_review-slide","name":"t:review_display_2","settings":{"show_on_display":"desktop_and_mobile","display_type":"2","wrap_in_card":true,"color_scheme":"scheme-2","show_card_border":true,"rating":4.5,"image_ratio":"landscape","source":"uploaded","video_url":"","title":"Excellent produit !","content":"<p>Écrivez un retour à propos de vos produits. Ajustez le nombre de colonnes en fonction de la taille moyenne des messages.<\/p>","author":"John Doe","date":"Le 11\/03\/2025","margin_top":0,"margin_bottom":0,"additional_class":""},"blocks":{}},"review_slide_3WHzH9":{"type":"_review-slide","name":"t:review_display_2","settings":{"show_on_display":"desktop_and_mobile","display_type":"2","wrap_in_card":true,"color_scheme":"scheme-2","show_card_border":true,"rating":4.5,"image_ratio":"landscape","source":"uploaded","video_url":"","title":"Excellent produit !","content":"<p>Écrivez un retour à propos de vos produits. Ajustez le nombre de colonnes en fonction de la taille moyenne des messages.<\/p>","author":"John Doe","date":"Le 11\/03\/2025","margin_top":0,"margin_bottom":0,"additional_class":""},"blocks":{}},"review_slide_xmGpjG":{"type":"_review-slide","name":"t:review_display_2","settings":{"show_on_display":"desktop_and_mobile","display_type":"2","wrap_in_card":true,"color_scheme":"scheme-2","show_card_border":true,"rating":4.5,"image_ratio":"landscape","source":"uploaded","video_url":"","title":"Excellent produit !","content":"<p>Écrivez un retour à propos de vos produits. Ajustez le nombre de colonnes en fonction de la taille moyenne des messages.<\/p>","author":"John Doe","date":"Le 11\/03\/2025","margin_top":0,"margin_bottom":0,"additional_class":""},"blocks":{}},"review_slide_hghqyx":{"type":"_review-slide","name":"t:review_display_2","settings":{"show_on_display":"desktop_and_mobile","display_type":"2","wrap_in_card":true,"color_scheme":"scheme-2","show_card_border":true,"rating":4.5,"image_ratio":"landscape","source":"uploaded","video_url":"","title":"Excellent produit !","content":"<p>Écrivez un retour à propos de vos produits. Ajustez le nombre de colonnes en fonction de la taille moyenne des messages.<\/p>","author":"John Doe","date":"Le 11\/03\/2025","margin_top":0,"margin_bottom":0,"additional_class":""},"blocks":{}},"review_slide_iAXYjY":{"type":"_review-slide","name":"t:review_display_2","settings":{"show_on_display":"desktop_and_mobile","display_type":"2","wrap_in_card":true,"color_scheme":"scheme-2","show_card_border":true,"rating":4.5,"image_ratio":"landscape","source":"uploaded","video_url":"","title":"Excellent produit !","content":"<p>Écrivez un retour à propos de vos produits. Ajustez le nombre de colonnes en fonction de la taille moyenne des messages.<\/p>","author":"John Doe","date":"Le 11\/03\/2025","margin_top":0,"margin_bottom":0,"additional_class":""},"blocks":{}},"review_slide_RXjByR":{"type":"_review-slide","name":"t:review_display_2","settings":{"show_on_display":"desktop_and_mobile","display_type":"2","wrap_in_card":true,"color_scheme":"scheme-2","show_card_border":true,"rating":4.5,"image_ratio":"landscape","source":"uploaded","video_url":"","title":"Excellent produit !","content":"<p>Écrivez un retour à propos de vos produits. Ajustez le nombre de colonnes en fonction de la taille moyenne des messages.<\/p>","author":"John Doe","date":"Le 11\/03\/2025","margin_top":0,"margin_bottom":0,"additional_class":""},"blocks":{}},"review_slide_Arkdc4":{"type":"_review-slide","name":"t:review_display_2","settings":{"show_on_display":"desktop_and_mobile","display_type":"2","wrap_in_card":true,"color_scheme":"scheme-2","show_card_border":true,"rating":4.5,"image_ratio":"landscape","source":"uploaded","video_url":"","title":"Excellent produit !","content":"<p>Écrivez un retour à propos de vos produits. Ajustez le nombre de colonnes en fonction de la taille moyenne des messages.<\/p>","author":"John Doe","date":"Le 11\/03\/2025","margin_top":0,"margin_bottom":0,"additional_class":""},"blocks":{}},"review_slide_hCCjhB":{"type":"_review-slide","name":"t:review_display_2","settings":{"show_on_display":"desktop_and_mobile","display_type":"2","wrap_in_card":true,"color_scheme":"scheme-2","show_card_border":true,"rating":4.5,"image_ratio":"landscape","source":"uploaded","video_url":"","title":"Excellent produit !","content":"<p>Écrivez un retour à propos de vos produits. Ajustez le nombre de colonnes en fonction de la taille moyenne des messages.<\/p>","author":"John Doe","date":"Le 11\/03\/2025","margin_top":0,"margin_bottom":0,"additional_class":""},"blocks":{}},"title":{"type":"text","static":true,"settings":{"show_on_display":"desktop_and_mobile","text":"<h3>Avis client<\/h3>","text_style":"h3","paragraph_font_size":"normal","font_weight":400,"alignment":"left","alignment_mobile":"left","show_read_more":false,"read_more_length":200,"read_more_text":"Voir plus","read_less_text":"Voir moins","truncate":false,"truncate_length":2,"margin_top":0,"margin_bottom":30,"additional_class":""},"blocks":{}}},"block_order":["review_slide_k9DNXe","review_slide_M9WWkF","review_slide_3WHzH9","review_slide_xmGpjG","review_slide_hghqyx","review_slide_iAXYjY","review_slide_RXjByR","review_slide_Arkdc4","review_slide_hCCjhB"],"disabled":true,"name":"t:reviews_grid","settings":{"show_on_display":"desktop_and_mobile","anchor":"reviews","layout_type":"grid","color_scheme":"scheme-1","grid_columns":3,"grid_columns_mobile":"1","slider_items":3,"slider_items_mobile":"1","show_arrows":false,"show_pagination":true,"rewind":false,"padding_top":50,"padding_bottom":50,"margin_top":0,"margin_bottom":0,"additional_class":""}},"1774342503f2e37486":{"type":"apps","blocks":{"judge_me_reviews_review_widget_bkcdMH":{"type":"shopify:\/\/apps\/judge-me-reviews\/blocks\/review_widget\/61ccd3b1-a9f2-4160-9fe9-4fec8413e5d8","settings":{"review_data":"real_data","max_width":1100,"show_shop_reviews":false,"empty_state":"empty_widget"}}},"block_order":["judge_me_reviews_review_widget_bkcdMH"],"settings":{}}},"order":["main","custom_section_xUHnaD","comparison_table_xRw3mt","custom_section_jGbBhQ","custom_section_Ng8LAT","custom_section_TDJcGh","custom_section_LBJBG7","reviews_8P6xW3","1774342503f2e37486"]}